pyrollout
