Metadata-Version: 1.0
Name: pyrollout
Version: 0.3.2
Summary: Feature flagging for your Python project
Home-page: https://github.com/brechin/pyrollout
Author: brechin
Author-email: brechinj@gmail.com
License: MIT
Platform: UNKNOWN
